{"id":146,"date":"2025-01-22T18:36:17","date_gmt":"2025-01-22T18:36:17","guid":{"rendered":"https:\/\/stg.linqresearchllc.com\/?page_id=146"},"modified":"2025-01-22T18:36:17","modified_gmt":"2025-01-22T18:36:17","slug":"join-clinical-research-study","status":"publish","type":"page","link":"https:\/\/stg.linqresearchllc.com\/join-clinical-research-study\/","title":{"rendered":"join clinical research study"},"content":{"rendered":"","protected":false},"excerpt":{"rendered":"","protected":false},"author":1,"featured_media":0,"parent":0,"menu_order":0,"comment_status":"closed","ping_status":"closed","template":"joinClinicalResearch.php","meta":{"footnotes":""},"class_list":["post-146","page","type-page","status-publish","hentry"],"_links":{"self":[{"href":"https:\/\/stg.linqresearchllc.com\/wp-json\/wp\/v2\/pages\/146","targetHints":{"allow":["GET"]}}],"collection":[{"href":"https:\/\/stg.linqresearchllc.com\/wp-json\/wp\/v2\/pages"}],"about":[{"href":"https:\/\/stg.linqresearchllc.com\/wp-json\/wp\/v2\/types\/page"}],"author":[{"embeddable":true,"href":"https:\/\/stg.linqresearchllc.com\/wp-json\/wp\/v2\/users\/1"}],"replies":[{"embeddable":true,"href":"https:\/\/stg.linqresearchllc.com\/wp-json\/wp\/v2\/comments?post=146"}],"version-history":[{"count":1,"href":"https:\/\/stg.linqresearchllc.com\/wp-json\/wp\/v2\/pages\/146\/revisions"}],"predecessor-version":[{"id":148,"href":"https:\/\/stg.linqresearchllc.com\/wp-json\/wp\/v2\/pages\/146\/revisions\/148"}],"wp:attachment":[{"href":"https:\/\/stg.linqresearchllc.com\/wp-json\/wp\/v2\/media?parent=146"}],"curies":[{"name":"wp","href":"https:\/\/api.w.org\/{rel}","templated":true}]}}